{"_class":"symbolMaster","frame":{"_class":"rect","constrainProportions":false,"height":14,"width":14,"x":343,"y":265.75},"allowsOverrides":true,"backgroundColor":{"_class":"color","red":1,"green":1,"blue":1,"alpha":1},"booleanOperation":-1,"changeIdentifier":0,"do_objectID":"UUID","symbolID":"UUID","exportOptions":{"_class":"exportOptions","includedLayerIds":[],"layerOptions":0,"shouldTrim":false,"exportFormats":[]},"hasClickThrough":true,"includeInCloudUpload":true,"hasBackgroundColor":false,"includeBackgroundColorInExport":true,"resizesContent":false,"includeBackgroundColorInInstance":false,"nameIsFixed":false,"shouldBreakMaskChain":false,"horizontalRulerData":{"_class":"rulerData","base":0,"guides":[]},"verticalRulerData":{"_class":"rulerData","base":0,"guides":[]},"resizingConstraint":1,"resizingType":1,"groupLayout":{"_class":"MSImmutableFreeformGroupLayout"},"isFixedToViewport":false,"sharedStyleID":"","isFlippedHorizontal":false,"isFlippedVertical":false,"isLocked":false,"isFlowHome":false,"name":"plus","rotation":0,"layerListExpandedType":0,"overrideProperties":[],"layers":[{"_class":"group","do_objectID":"UUID","booleanOperation":-1,"isFixedToViewport":false,"isFlippedHorizontal":false,"isFlippedVertical":false,"isVisible":true,"isLocked":false,"layerListExpandedType":0,"name":"plus","nameIsFixed":false,"resizingConstraint":63,"resizingType":0,"rotation":0,"shouldBreakMaskChain":false,"exportOptions":{"_class":"exportOptions","includedLayerIds":[],"layerOptions":0,"shouldTrim":false,"exportFormats":[]},"frame":{"_class":"rect","constrainProportions":false,"height":14,"width":14,"x":0,"y":0},"clippingMaskMode":0,"hasClippingMask":false,"style":{"_class":"style","do_objectID":"UUID","endMarkerType":0,"miterLimit":10,"startMarkerType":0,"windingRule":1,"borderOptions":{"_class":"borderOptions","isEnabled":true,"dashPattern":[],"lineCapStyle":0,"lineJoinStyle":0},"colorControls":{"_class":"colorControls","isEnabled":false,"brightness":0,"contrast":1,"hue":0,"saturation":1},"fills":[],"borders":[],"shadows":[],"innerShadows":[],"contextSettings":{"_class":"graphicsContextSettings","blendMode":0,"opacity":1}},"hasClickThrough":false,"groupLayout":{"_class":"MSImmutableFreeformGroupLayout"},"layers":[{"_class":"rectangle","name":"容器","resizingConstraint":63,"frame":{"_class":"rect","constrainProportions":false,"height":14,"width":14,"x":0,"y":0},"do_objectID":"UUID","hasConvertedToNewRoundCorners":true,"needsConvertionToNewRoundCorners":false,"fixedRadius":0,"style":{"_class":"style","do_objectID":"UUID","endMarkerType":0,"miterLimit":10,"startMarkerType":0,"windingRule":1,"borderOptions":{"_class":"borderOptions","isEnabled":true,"dashPattern":[],"lineCapStyle":0,"lineJoinStyle":0},"colorControls":{"_class":"colorControls","isEnabled":false,"brightness":0,"contrast":1,"hue":0,"saturation":1},"fills":[],"borders":[],"shadows":[],"innerShadows":[],"contextSettings":{"_class":"graphicsContextSettings","blendMode":0,"opacity":1}},"edited":false,"pointRadiusBehaviour":1,"points":[{"_class":"curvePoint","cornerRadius":0,"curveFrom":"{0, 0}","curveMode":1,"curveTo":"{0, 0}","hasCurveFrom":false,"hasCurveTo":false,"point":"{0, 0}"},{"_class":"curvePoint","cornerRadius":0,"curveFrom":"{1, 0}","curveMode":1,"curveTo":"{1, 0}","hasCurveFrom":false,"hasCurveTo":false,"point":"{1, 0}"},{"_class":"curvePoint","cornerRadius":0,"curveFrom":"{1, 1}","curveMode":1,"curveTo":"{1, 1}","hasCurveFrom":false,"hasCurveTo":false,"point":"{1, 1}"},{"_class":"curvePoint","cornerRadius":0,"curveFrom":"{0, 1}","curveMode":1,"curveTo":"{0, 1}","hasCurveFrom":false,"hasCurveTo":false,"point":"{0, 1}"}],"isClosed":true,"booleanOperation":-1,"exportOptions":{"_class":"exportOptions","includedLayerIds":[],"layerOptions":0,"shouldTrim":false,"exportFormats":[]},"isVisible":true,"isFixedToViewport":false,"isFlippedHorizontal":false,"isFlippedVertical":false,"layerListExpandedType":0,"nameIsFixed":false,"resizingType":0,"rotation":0,"shouldBreakMaskChain":false,"clippingMaskMode":0,"isLocked":false,"hasClippingMask":true},{"_class":"shapePath","booleanOperation":-1,"do_objectID":"UUID","rotation":0,"isVisible":true,"isFixedToViewport":false,"isFlippedHorizontal":false,"isFlippedVertical":false,"layerListExpandedType":0,"nameIsFixed":false,"resizingType":0,"shouldBreakMaskChain":false,"clippingMaskMode":0,"isLocked":false,"exportOptions":{"_class":"exportOptions","includedLayerIds":[],"layerOptions":0,"shouldTrim":false,"exportFormats":[]},"frame":{"_class":"rect","constrainProportions":false,"height":11.25,"width":1.1875,"x":6.40625,"y":1.3749999999999996},"name":"路径","style":{"_class":"style","do_objectID":"UUID","endMarkerType":0,"miterLimit":10,"startMarkerType":0,"windingRule":1,"borderOptions":{"_class":"borderOptions","isEnabled":true,"dashPattern":[],"lineCapStyle":0,"lineJoinStyle":0},"colorControls":{"_class":"colorControls","isEnabled":false,"brightness":0,"contrast":1,"hue":0,"saturation":1},"fills":[{"_class":"fill","isEnabled":true,"fillType":0,"color":{"_class":"color","red":0,"green":0,"blue":0,"alpha":0.85},"contextSettings":{"_class":"graphicsContextSettings","blendMode":0,"opacity":1},"gradient":{"_class":"gradient","elipseLength":0,"from":"{0.5, 0}","gradientType":0,"to":"{0.5, 1}","stops":[]},"noiseIndex":0,"noiseIntensity":0,"patternFillType":1,"patternTileScale":1}],"borders":[],"shadows":[],"innerShadows":[],"contextSettings":{"_class":"graphicsContextSettings","blendMode":0,"opacity":1}},"resizingConstraint":63,"edited":true,"isClosed":true,"points":[{"_class":"curvePoint","cornerRadius":0,"curveFrom":"{0.10526315789473684, 3.947459643111668e-17}","curveMode":4,"curveTo":"{0.03508771929824561, 3.947459643111668e-17}","hasCurveFrom":false,"hasCurveTo":true,"point":"{0.10526315789473684, 3.947459643111668e-17}"},{"_class":"curvePoint","cornerRadius":0,"curveFrom":"{0.9649122807017543, 3.947459643111668e-17}","curveMode":4,"curveTo":"{0.8947368421052632, 3.947459643111668e-17}","hasCurveFrom":true,"hasCurveTo":false,"point":"{0.8947368421052632, 3.947459643111668e-17}"},{"_class":"curvePoint","cornerRadius":0,"curveFrom":"{1, 0.011111111111111151}","curveMode":4,"curveTo":"{1, 0.003703703703703743}","hasCurveFrom":false,"hasCurveTo":true,"point":"{1, 0.011111111111111151}"},{"_class":"curvePoint","cornerRadius":0,"curveFrom":"{1, 0.9962962962962963}","curveMode":4,"curveTo":"{1, 0.9888888888888889}","hasCurveFrom":true,"hasCurveTo":false,"point":"{1, 0.9888888888888889}"},{"_class":"curvePoint","cornerRadius":0,"curveFrom":"{0.8947368421052632, 1}","curveMode":4,"curveTo":"{0.9649122807017543, 1}","hasCurveFrom":false,"hasCurveTo":true,"point":"{0.8947368421052632, 1}"},{"_class":"curvePoint","cornerRadius":0,"curveFrom":"{0.03508771929824561, 1}","curveMode":4,"curveTo":"{0.10526315789473684, 1}","hasCurveFrom":true,"hasCurveTo":false,"point":"{0.10526315789473684, 1}"},{"_class":"curvePoint","cornerRadius":0,"curveFrom":"{0, 0.9888888888888889}","curveMode":4,"curveTo":"{0, 0.9962962962962963}","hasCurveFrom":false,"hasCurveTo":true,"point":"{0, 0.9888888888888889}"},{"_class":"curvePoint","cornerRadius":0,"curveFrom":"{0, 0.003703703703703743}","curveMode":4,"curveTo":"{0, 0.011111111111111151}","hasCurveFrom":true,"hasCurveTo":false,"point":"{0, 0.011111111111111151}"}],"pointRadiusBehaviour":1},{"_class":"shapePath","booleanOperation":-1,"do_objectID":"UUID","rotation":0,"isVisible":true,"isFixedToViewport":false,"isFlippedHorizontal":false,"isFlippedVertical":false,"layerListExpandedType":0,"nameIsFixed":false,"resizingType":0,"shouldBreakMaskChain":false,"clippingMaskMode":0,"isLocked":false,"exportOptions":{"_class":"exportOptions","includedLayerIds":[],"layerOptions":0,"shouldTrim":false,"exportFormats":[]},"frame":{"_class":"rect","constrainProportions":false,"height":1.1875,"width":10.75,"x":1.625,"y":6.40625},"name":"路径","style":{"_class":"style","do_objectID":"UUID","endMarkerType":0,"miterLimit":10,"startMarkerType":0,"windingRule":1,"borderOptions":{"_class":"borderOptions","isEnabled":true,"dashPattern":[],"lineCapStyle":0,"lineJoinStyle":0},"colorControls":{"_class":"colorControls","isEnabled":false,"brightness":0,"contrast":1,"hue":0,"saturation":1},"fills":[{"_class":"fill","isEnabled":true,"fillType":0,"color":{"_class":"color","red":0,"green":0,"blue":0,"alpha":0.85},"contextSettings":{"_class":"graphicsContextSettings","blendMode":0,"opacity":1},"gradient":{"_class":"gradient","elipseLength":0,"from":"{0.5, 0}","gradientType":0,"to":"{0.5, 1}","stops":[]},"noiseIndex":0,"noiseIntensity":0,"patternFillType":1,"patternTileScale":1}],"borders":[],"shadows":[],"innerShadows":[],"contextSettings":{"_class":"graphicsContextSettings","blendMode":0,"opacity":1}},"resizingConstraint":63,"edited":true,"isClosed":true,"points":[{"_class":"curvePoint","cornerRadius":0,"curveFrom":"{0.011627906976744186, 0}","curveMode":4,"curveTo":"{0.003875968992248062, 0}","hasCurveFrom":false,"hasCurveTo":true,"point":"{0.011627906976744186, 0}"},{"_class":"curvePoint","cornerRadius":0,"curveFrom":"{0.996124031007752, 0}","curveMode":4,"curveTo":"{0.9883720930232558, 0}","hasCurveFrom":true,"hasCurveTo":false,"point":"{0.9883720930232558, 0}"},{"_class":"curvePoint","cornerRadius":0,"curveFrom":"{1, 0.10526315789473684}","curveMode":4,"curveTo":"{1, 0.03508771929824561}","hasCurveFrom":false,"hasCurveTo":true,"point":"{1, 0.10526315789473684}"},{"_class":"curvePoint","cornerRadius":0,"curveFrom":"{1, 0.9649122807017543}","curveMode":4,"curveTo":"{1, 0.8947368421052632}","hasCurveFrom":true,"hasCurveTo":false,"point":"{1, 0.8947368421052632}"},{"_class":"curvePoint","cornerRadius":0,"curveFrom":"{0.9883720930232558, 1}","curveMode":4,"curveTo":"{0.996124031007752, 1}","hasCurveFrom":false,"hasCurveTo":true,"point":"{0.9883720930232558, 1}"},{"_class":"curvePoint","cornerRadius":0,"curveFrom":"{0.003875968992248062, 1}","curveMode":4,"curveTo":"{0.011627906976744186, 1}","hasCurveFrom":true,"hasCurveTo":false,"point":"{0.011627906976744186, 1}"},{"_class":"curvePoint","cornerRadius":0,"curveFrom":"{0, 0.8947368421052632}","curveMode":4,"curveTo":"{0, 0.9649122807017543}","hasCurveFrom":false,"hasCurveTo":true,"point":"{0, 0.8947368421052632}"},{"_class":"curvePoint","cornerRadius":0,"curveFrom":"{0, 0.03508771929824561}","curveMode":4,"curveTo":"{0, 0.10526315789473684}","hasCurveFrom":true,"hasCurveTo":false,"point":"{0, 0.10526315789473684}"}],"pointRadiusBehaviour":1}]}],"isVisible":true}